kotori/__init__.py
kotori/core.py
kotori/version.py
kotori/bus/__init__.py
kotori/bus/wamp.py
kotori/daq/__init__.py
kotori/daq/application/__init__.py
kotori/daq/application/basic.py
kotori/daq/application/composite.py
kotori/daq/application/mqttkit.py
kotori/daq/decoder/__init__.py
kotori/daq/decoder/airrohr.py
kotori/daq/decoder/schema.py
kotori/daq/decoder/tasmota.py
kotori/daq/graphing/__init__.py
kotori/daq/graphing/grafana/__init__.py
kotori/daq/graphing/grafana/api.py
kotori/daq/graphing/grafana/dashboard.py
kotori/daq/graphing/grafana/manager.py
kotori/daq/graphing/grafana/service.py
kotori/daq/graphing/grafana/resources/grafana-annotation.json
kotori/daq/graphing/grafana/resources/grafana-dashboard.json
kotori/daq/graphing/grafana/resources/grafana-panel.json
kotori/daq/graphing/grafana/resources/grafana-target.json
kotori/daq/intercom/__init__.py
kotori/daq/intercom/c.py
kotori/daq/intercom/udp.py
kotori/daq/intercom/wamp.py
kotori/daq/intercom/mqtt/__init__.py
kotori/daq/intercom/mqtt/base.py
kotori/daq/intercom/mqtt/paho.py
kotori/daq/intercom/mqtt/twisted.py
kotori/daq/intercom/pyclibrary_ext/__init__.py
kotori/daq/intercom/pyclibrary_ext/backend_ctypes.py
kotori/daq/intercom/pyclibrary_ext/c_parser.py
kotori/daq/services/__init__.py
kotori/daq/services/mig.py
kotori/daq/storage/__init__.py
kotori/daq/storage/influx.py
kotori/daq/strategy/__init__.py
kotori/daq/strategy/lan.py
kotori/daq/strategy/wan.py
kotori/firmware/__init__.py
kotori/firmware/builder.py
kotori/firmware/service.py
kotori/frontend/__init__.py
kotori/frontend/app.py
kotori/frontend/server.py
kotori/frontend/views.py
kotori/frontend/templates/index.html
kotori/io/__init__.py
kotori/io/export/__init__.py
kotori/io/export/html.py
kotori/io/export/influx.py
kotori/io/export/plot.py
kotori/io/export/tabular.py
kotori/io/export/util.py
kotori/io/export/vega_template.html
kotori/io/protocol/__init__.py
kotori/io/protocol/forwarder.py
kotori/io/protocol/http.py
kotori/io/protocol/influx.py
kotori-0.27.0.dist-info/LICENSE
kotori-0.27.0.dist-info/METADATA
kotori-0.27.0.dist-info/WHEEL
kotori-0.27.0.dist-info/entry_points.txt
kotori-0.27.0.dist-info/top_level.txt
kotori-0.27.0.dist-info/RECORD
