Metadata-Version: 2.1
Name: kotori
Version: 0.27.0
Summary: Kotori is a data acquisition, processing and graphing toolkit for humans
Home-page: https://github.com/daq-tools/kotori
Author: Andreas Motl
Author-email: andreas.motl@getkotori.org
License: AGPL 3, EUPL 1.2
Keywords: data acquisition graphing export plotting daq routing engine mqtt http rest amqp wamp sql web html csv json cdf hdf5 png twisted pyramid autobahn influxdb mosquitto grafana mongodb matplotlib ggplot telemetry m2m iot
Classifier: Programming Language :: Python
Classifier: Programming Language :: Python :: 3
Classifier: Programming Language :: Python :: 3.7
Classifier: Programming Language :: Python :: 3.8
Classifier: Programming Language :: Python :: 3.9
Classifier: Programming Language :: Python :: 3.10
Classifier: Programming Language :: Python :: 3.11
Classifier: Programming Language :: Python :: Implementation :: CPython
Classifier: Programming Language :: Python :: Implementation :: PyPy
Classifier: License :: OSI Approved :: GNU Affero General Public License v3
Classifier: License :: OSI Approved :: European Union Public Licence 1.2 (EUPL 1.2)
Classifier: Development Status :: 5 - Production/Stable
Classifier: Environment :: Console
Classifier: Environment :: Web Environment
Classifier: Framework :: Pyramid
Classifier: Framework :: Twisted
Classifier: Intended Audience :: Developers
Classifier: Intended Audience :: Education
Classifier: Intended Audience :: Information Technology
Classifier: Intended Audience :: Manufacturing
Classifier: Intended Audience :: Science/Research
Classifier: Intended Audience :: System Administrators
Classifier: Intended Audience :: Telecommunications Industry
Classifier: Topic :: Communications
Classifier: Topic :: Database
Classifier: Topic :: Internet
Classifier: Topic :: Internet :: WWW/HTTP
Classifier: Topic :: Internet :: WWW/HTTP :: HTTP Servers
Classifier: Topic :: Internet :: WWW/HTTP :: WSGI
Classifier: Topic :: Scientific/Engineering :: Atmospheric Science
Classifier: Topic :: Scientific/Engineering :: GIS
Classifier: Topic :: Scientific/Engineering :: Human Machine Interfaces
Classifier: Topic :: Scientific/Engineering :: Information Analysis
Classifier: Topic :: Scientific/Engineering :: Interface Engine/Protocol Translator
Classifier: Topic :: Scientific/Engineering :: Visualization
Classifier: Topic :: Software Development :: Embedded Systems
Classifier: Topic :: Software Development :: Libraries
Classifier: Topic :: Software Development :: Object Brokering
Classifier: Topic :: System :: Archiving
Classifier: Topic :: System :: Networking :: Monitoring
Classifier: Topic :: Text Processing
Classifier: Topic :: Utilities
Classifier: Operating System :: POSIX
Classifier: Operating System :: Unix
Classifier: Operating System :: MacOS
License-File: LICENSE
Requires-Dist: Twisted[tls] (<23)
Requires-Dist: pyOpenSSL (>=16.2.0)
Requires-Dist: six (>=1.15.0)
Requires-Dist: pyramid (==1.10.8)
Requires-Dist: pyramid-jinja2 (<3,>=2.8)
Requires-Dist: cornice (<6,>=5.0.3)
Requires-Dist: simplejson (<4,>=3.17.2)
Requires-Dist: Jinja2 (<4)
Requires-Dist: munch (<3,>=2.5.0)
Requires-Dist: appdirs (<2,>=1.4.3)
Requires-Dist: json-store (<4,>=3.1)
Requires-Dist: python-dateutil (<3,>=2.8.0)
Requires-Dist: arrow (<2,>=0.17.0)
Requires-Dist: funcy (<2,>=1.15)
Requires-Dist: attrs (<22,>=20.2.0)
Requires-Dist: paho-mqtt (<2,>=1.5.1)
Requires-Dist: autobahn[twisted] (<21,>=20.7.1)
Requires-Dist: msgpack-python (<0.6,>=0.5.6)
Requires-Dist: PyTrie (<1,>=0.4.0)
Requires-Dist: distlib (<0.4,>=0.3.1)
Requires-Dist: docopt (<0.7,>=0.6.2)
Requires-Dist: cryptography (>=2.9.2)
Requires-Dist: certifi (>=2020.6.20)
Requires-Dist: service-identity (<22,>=18.1.0)
Requires-Dist: idna (<4,>=2.10)
Requires-Dist: pyasn1 (<0.5,>=0.4.8)
Requires-Dist: pyasn1-modules (<0.3,>=0.2.8)
Provides-Extra: daq
Requires-Dist: influxdb (<6,>=5.3.0) ; extra == 'daq'
Requires-Dist: pytz (>=2020.1) ; extra == 'daq'
Requires-Dist: requests (<3,>=2.12.4) ; extra == 'daq'
Requires-Dist: grafana-api-client (==0.2.0) ; extra == 'daq'
Requires-Dist: pymongo (<5,>=3.11.0) ; extra == 'daq'
Provides-Extra: daq_binary
Requires-Dist: pycparser (==2.17) ; extra == 'daq_binary'
Requires-Dist: pyparsing (==2.2.0) ; extra == 'daq_binary'
Requires-Dist: pyclibrary (==0.1.3) ; extra == 'daq_binary'
Requires-Dist: tabulate (==0.7.5) ; extra == 'daq_binary'
Requires-Dist: sympy (==0.7.6.1) ; extra == 'daq_binary'
Provides-Extra: daq_geospatial
Requires-Dist: Geohash (<2,>=1.0) ; extra == 'daq_geospatial'
Requires-Dist: geopy (<3,>=1.12.0) ; extra == 'daq_geospatial'
Requires-Dist: Beaker (<2,>=1.9.0) ; extra == 'daq_geospatial'
Requires-Dist: tqdm (<5,>=4.19.8) ; extra == 'daq_geospatial'
Provides-Extra: export
Requires-Dist: pyinfluxql (<1,>=0.0.1) ; extra == 'export'
Requires-Dist: pandas (<1.3) ; extra == 'export'
Requires-Dist: numpy (<1.22,>=1.18) ; extra == 'export'
Requires-Dist: XlsxWriter (<4,>=1.3.6) ; extra == 'export'
Provides-Extra: firmware
Requires-Dist: GitPython (<3,>=2.0.5) ; extra == 'firmware'
Requires-Dist: plumbum (<1.7,>=1.6.1) ; extra == 'firmware'
Provides-Extra: plotting
Requires-Dist: matplotlib (<3.4,>=3) ; extra == 'plotting'
Requires-Dist: bokeh (<2.3,>=1.4.0) ; extra == 'plotting'
Requires-Dist: vincent (<0.5,>=0.4.4) ; extra == 'plotting'
Provides-Extra: scientific
Requires-Dist: xarray (<0.22,>=0.13.0) ; extra == 'scientific'
Requires-Dist: netCDF4 (<1.7,>=1.5.3) ; extra == 'scientific'
Requires-Dist: ggplot (<0.12,>=0.11.5) ; extra == 'scientific'
Requires-Dist: h5py (<4,>=2.10.0) ; extra == 'scientific'
Requires-Dist: tables (<4,>=3.5.2) ; extra == 'scientific'
Provides-Extra: storage_plus
Requires-Dist: alchimia (<1,>=0.4) ; extra == 'storage_plus'
